setup.py
git_covdiff.egg-info/PKG-INFO
git_covdiff.egg-info/SOURCES.txt
git_covdiff.egg-info/dependency_links.txt
git_covdiff.egg-info/entry_points.txt
git_covdiff.egg-info/requires.txt
git_covdiff.egg-info/top_level.txt
gitcovdiff/__init__.py