Metadata-Version: 1.0
Name: git-covdiff
Version: 0.0.1
Summary: Highlight newly appeared coverage missing in latest changeset in git.
Home-page: https://github.com/nttmcl/git-covdiff
Author: Yusuke MURAOKA
Author-email: yusuke@nttmcl.com
License: BSD
Keywords: git coverage
Platform: UNKNOWN
Classifier: Development Status :: 3 - Alpha
Classifier: Environment :: Console
Classifier: Topic :: Utilities
Classifier: License :: OSI Approved :: BSD License
